vault/VERSION
vault/__init__.py
vault/__version__.py
vault/v1.py
vault/v2.py
vault/vault.py
vault/vault_base.py
cnd_vault-0.1.1.dist-info/METADATA
cnd_vault-0.1.1.dist-info/WHEEL
cnd_vault-0.1.1.dist-info/top_level.txt
cnd_vault-0.1.1.dist-info/RECORD
